RetroScore/__init__.py
RetroScore/retros.py
RetroScore/data/multi_step/retro_data/saved_models/best_epoch_final_4.pt
RetroScore/experiments/uspto_full/epoch_65.pt
RetroScore/graph2edits/__init__.py
RetroScore/graph2edits/canonicalize_prod.py
RetroScore/graph2edits/prepare_data.py
RetroScore/graph2edits/preprocess.py
RetroScore/graph2edits/train.py
RetroScore/models/__init__.py
RetroScore/models/beam_search.py
RetroScore/models/encoder.py
RetroScore/models/graph2edits.py
RetroScore/models/model_utils.py
RetroScore/retro_star/__init__.py
RetroScore/retro_star/alg/__init__.py
RetroScore/retro_star/alg/mol_node.py
RetroScore/retro_star/alg/mol_tree.py
RetroScore/retro_star/alg/molstar.py
RetroScore/retro_star/alg/reaction_node.py
RetroScore/retro_star/alg/syn_route.py
RetroScore/retro_star/common/__init__.py
RetroScore/retro_star/common/prepare_utils.py
RetroScore/retro_star/common/smiles_to_fp.py
RetroScore/retro_star/model/__init__.py
RetroScore/retro_star/model/value_mlp.py
RetroScore/retro_star/utils/__init__.py
RetroScore/retro_star/utils/logger.py
RetroScore/utils/__init__.py
RetroScore/utils/calculate_edit_distance.py
RetroScore/utils/chem.py
RetroScore/utils/collate_fn.py
RetroScore/utils/datasets.py
RetroScore/utils/generate_edits.py
RetroScore/utils/mol_features.py
RetroScore/utils/reaction_actions.py
RetroScore/utils/rxn_graphs.py
retroscore-1.2.dist-info/METADATA
retroscore-1.2.dist-info/WHEEL
retroscore-1.2.dist-info/top_level.txt
retroscore-1.2.dist-info/RECORD
